Metadata-Version: 2.1
Name: topsis-Srishti-101903715
Version: 1.1
Summary: A Python package to rank ML models/choices using topsis technique
Home-page: UNKNOWN
Author: Srishti Vermani
Author-email: ssrishti_be19@thapar.edu
License: MIT
Platform: UNKNOWN
Classifier: License :: OSI Approved :: MIT License
Classifier: Programming Language :: Python :: 3
Classifier: Programming Language :: Python :: 3.7
